Workbook

Sheet 様式１　プログラムを構成する授業科目
T1: 様式１ | V1: 「学部・学科によって、修了要件は相違する」場合は、本シートを複製の上＜様式１－〇＞と枝番号を付してください
B2: 大学等名 | C2: 吉備国際大学
B3: プログラム名 | C3: 数理・データサイエンス・AI教育プログラム（リテラシーレベル）
A5: プログラムを構成する授業科目について
A7: ① 教育プログラムの修了要件 | L7: 学部・学科によって、修了要件は相違しない
A9: ② 対象となる学部・学科名称
A14: ③ 修了要件
B15: プログラムを構成する2つの科目「数理・データサイエンス・AI基礎」（1年次秋学期配当、2単位）と「数理・データサイエンス・AI応用（オンライン）」（2年次春学期配当、2単位）をいずれも修得すること。 | W15: 【プルダウンリスト】
W16: 令和５年度以前より、履修することが必須のプログラムとして実施
W17: 令和８年度までに履修必須とする計画
W18: 令和９年度以降に履修必須とする計画、又は未定
B22: 必要最低科目数・単位数 | E22: 2 | F22: 科目 | H22: 4 | I22: 単位 | M22: 履修必須の有無 | N22: 令和８年度までに履修必須とする計画
A24: ④ 現在進行中の社会変化（第４次産業革命、Society 5.0、データ駆動型社会等）に深く寄与しているものであり、それが自らの生活と密接に結びついている」の内容を含む授業科目
B26: 授業科目 | G26: 単位数 | H26: 必須 | I26: 1-1 | J26: 1-6 | K26: 授業科目 | R26: 単位数 | S26: 必須 | T26: 1-1 | U26: 1-6
B27: 数理・データサイエンス・AI基礎 | G27: 2 | H27: ○ | I27: ○ | J27: ○
A35: ⑤ 「社会で活用されているデータ」や「データの活用領域」は非常に広範囲であって、日常生活や社会の課題を解決する有用なツールになり得るもの」の内容を含む授業科目
B37: 授業科目 | G37: 単位数 | H37: 必須 | I37: 1-2 | J37: 1-3 | K37: 授業科目 | R37: 単位数 | S37: 必須 | T37: 1-2 | U37: 1-3
B38: 数理・データサイエンス・AI基礎 | G38: 2 | H38: ○ | I38: ○ | J38: ○
A46: ⑥ 「様々なデータ利活用の現場におけるデータ利活用事例が示され、様々な適用領域（流通、製造、金融、サービス、インフラ、公共、ヘルスケア等）の知見と組み合わせることで価値を創出するもの」の内容を含む授業科目
B48: 授業科目 | G48: 単位数 | H48: 必須 | I48: 1-4 | J48: 1-5 | K48: 授業科目 | R48: 単位数 | S48: 必須 | T48: 1-4 | U48: 1-5
B49: 数理・データサイエンス・AI基礎 | G49: 2 | H49: ○ | I49: ○ | J49: ○
A57: ⑦ 「活用に当たっての様々な留意事項（ELSI、個人情報、データ倫理、ＡＩ社会原則等）を考慮し、情報セキュリティや情報漏洩等、データを守る上での留意事項への理解をする」の内容を含む授業科目
B59: 授業科目 | G59: 単位数 | H59: 必須 | I59: 3-1 | J59: 3-2 | K59: 授業科目 | R59: 単位数 | S59: 必須 | T59: 3-1 | U59: 3-2
B60: 数理・データサイエンス・AI基礎 | G60: 2 | H60: ○ | I60: ○ | J60: ○
A68: ⑧ 「実データ・実課題（学術データ等を含む）を用いた演習など、社会での実例を題材として、「データを読む、説明する、扱う」といった数理・データサイエンス・ＡＩの基本的な活用法に関するもの」の内容を含む授業科目
B70: 授業科目 | F70: 単位数 | G70: 必須 | H70: 2-1 | I70: 2-2 | J70: 2-3 | K70: 授業科目 | Q70: 単位数 | R70: 必須 | S70: 2-1 | T70: 2-2 | U70: 2-3
B71: 数理・データサイエンス・AI基礎 | F71: 2 | G71: ○ | H71: ○ | I71: ○ | J71: ○
B72: 数理・データサイエンス・AI応用 | F72: 2 | G72: ○ | H72: ○ | I72: ○ | J72: ○
A79: ⑨ 選択「４．オプション」の内容を含む授業科目
B80: 授業科目 | G80: 選択項目 | K80: 授業科目 | R80: 選択項目
B81: 数理・データサイエンス・AI基礎 | G81: 4‐3データ構造とプログラミング基礎 | K81: 数理・データサイエンス・AI応用 | R81: 4‐9データ活用実践（教師なし学習）
B82: 数理・データサイエンス・AI基礎 | G82: 4‐7データハンドリング
B83: 数理・データサイエンス・AI基礎 | G83: 4‐8データ活用実践（教師あり学習）
B84: 数理・データサイエンス・AI基礎 | G84: 4‐9データ活用実践（教師なし学習）
B85: 数理・データサイエンス・AI応用 | G85: 4‐3データ構造とプログラミング基礎
B86: 数理・データサイエンス・AI応用 | G86: 4‐7データハンドリング
B87: 数理・データサイエンス・AI応用 | G87: 4‐8データ活用実践（教師あり学習）
A89: ⑩ プログラムを構成する授業の内容
B90: 授業に含まれている内容・要素 | D90: 講義内容
B91: （１）現在進行中の社会変化（第４次産業革命、Society 5.0、データ駆動型社会等）に深く寄与しているものであり、それが自らの生活と密接に結びついている | C91: 1-1 | D91: ・ビッグデータ、IoT、AI、ロボット「数理・データサイエンス・AI基礎」（第1回、第2回、第3回） ・データ量の増加、計算機の処理性能の向上、AIの非連続的進化「数理・データサイエンス・AI基礎」（第1回、第5回） ・第4次産業革命、Society5.0、データ駆動型社会「数理・データサイエンス・AI基礎」（第2回、第3回）
C92: 1-6 | D92: ・AI最新技術の活用例（深層生成モデル、敵対的生成ネットワーク、強化学習、転移学習など）「数理・データサイエンス・AI基礎」（第1回、第5回）
B93: （２）「社会で活用されているデータ」や「データの活用領域」は非常に広範囲であって、日常生活や社会の課題を解決する有用なツールになり得るもの | C93: 1-2 | D93: ・調査データ、実験データ、人の行動ログデータ、機械の稼働ログデータなど「数理・データサイエンス・AI基礎」（第3回、第6回） ・1次データ、2次データ、データのメタ化「数理・データサイエンス・AI基礎」（第3回） ・構造化データ、非構造化データ（文章、画像/動画、音声/音楽など）「数理・データサイエンス・AI基礎」（第6回） ・データ作成（ビッグデータとアノテーション）「数理・データサイエンス・AI基礎」（第6回） ・データのオープン化（オープンデータ）「数理・データサイエンス・AI基礎」（第6回）
C94: 1-3 | D94: ・データ・AI活用領域の広がり(生産、消費、文化活動など)「数理・データサイエンス・AI基礎」（第3回、第4回） ・研究開発、調達、製造、物流、販売、マーケティング、サービスなど「数理・データサイエンス・AI基礎」（第3回） ・仮説検証、知識発見、原因究明、計画策定、判断支援、活動代替、新規生成など「数理・データサイエンス・AI基礎」（第3回）
B95: （３）様々なデータ利活用の現場におけるデータ利活用事例が示され、様々な適用領域（流通、製造、金融、サービス、インフラ、公共、ヘルスケア等）の知見と組み合わせることで価値を創出するもの | C95: 1-4 | D95: ・特化型AIと汎用AI、今のAIで出来ることと出来ないこと、AIとビッグデータ「数理・データサイエンス・AI基礎」（第1回、第5回） ・認識技術、ルールベース、自動化技術「数理・データサイエンス・AI基礎」（第1回、第5回、第10回）
C96: 1-5 | D96: ・流通、製造、金融、サービス、インフラ、公共、ヘルスケア等におけるデータ・AI利活用事例紹介「数理・データサイエンス・AI基礎」（第3回、第4回）
B97: （４）活用に当たっての様々な留意事項（ELSI、個人情報、データ倫理、ＡＩ社会原則等）を考慮し、情報セキュリティや情報漏洩等、データを守る上での留意事項への理解をする | C97: 3-1 | D97: ・ELSI（Ethical, Legal and Social Issues）「数理・データサイエンス・AI基礎」（第2回、第7回、第8回） ・個人情報保護、EU一般データ保護規則(GDPR)、忘れられる権利、オプトアウト「数理・データサイエンス・AI基礎」（第7回、第8回） ・データ倫理：データのねつ造、改ざん、盗用、プライバシー保護「数理・データサイエンス・AI基礎」（第7回、第8回） ・AI社会原則（公平性、説明責任、透明性、人間中心の判断）「数理・データサイエンス・AI基礎」（第2回、第7回、第8回） ・データバイアス、アルゴリズムバイアス「数理・データサイエンス・AI基礎」（第2回、第7回、第8回） ・データ・AI活用における負の事例紹介「数理・データサイエンス・AI基礎」（第2回、第7回、第8回）
C98: 3-2 | D98: ・情報セキュリティ：機密性、完全性、可用性「数理・データサイエンス・AI基礎」（第8回） ・匿名加工情報、暗号化、パスワード、悪意ある情報搾取「数理・データサイエンス・AI基礎」（第8回、第9回） ・情報漏洩等によるセキュリティ事故の事例紹介「数理・データサイエンス・AI基礎」（第9回）
B99: （５）実データ・実課題（学術データ等を含む）を用いた演習など、社会での実例を題材として、「データを読む、説明する、扱う」といった数理・データサイエンス・ＡＩの基本的な活用法に関するもの | C99: 2-1 | D99: ・データの種類（量的変数、質的変数）「数理・データサイエンス・AI基礎」（第6回） ・データの分布（ヒストグラム）と代表値（平均値、中央値、最頻値）「数理・データサイエンス・AI基礎」（第6回、第9回）「数理・データサイエンス・AI応用」（第2回） ・代表値の性質の違い（実社会では平均値＝最頻値でないことが多い）「数理・データサイエンス・AI基礎」（第6回、第9回）「数理・データサイエンス・AI応用」（第2回） ・データのばらつき（分散、標準偏差、偏差値）「数理・データサイエンス・AI基礎」（第6回、第9回）「数理・データサイエンス・AI応用」（第3回、第4回、第5回） ・相関と因果（相関係数、疑似相関、交絡）「数理・データサイエンス・AI応用」（第5回） ・母集団と標本抽出（国勢調査、アンケート調査、全数調査、単純無作為抽出、層別抽出、多段抽出）「数理・データサイエンス・AI応用」（第1回）
C100: 2-2 | D100: ・データ表現（棒グラフ、折線グラフ、散布図、ヒートマップ）「数理・データサイエンス・AI基礎」（第5回、第6回）「数理・データサイエンス・AI応用」（第3回） ・データの図表表現（チャート化）「数理・データサイエンス・AI基礎」（第5回、第6回）「数理・データサイエンス・AI応用」（第5回） ・優れた可視化事例の紹介（可視化することによって新たな気づきがあった事例など）「数理・データサイエンス・AI基礎」（第6回、第9回）「数理・データサイエンス・AI応用」（第5回）
C101: 2-3 | D101: ・データの集計（和、平均）「数理・データサイエンス・AI応用」（第2回） ・データの並び替え、ランキング「数理・データサイエンス・AI応用」（第2回、第3回） ・データ解析ツール（スプレッドシート）「数理・データサイエンス・AI応用」（第4回、第5回、第6回） ・表形式のデータ（csv）「数理・データサイエンス・AI基礎」（第12回）「数理・データサイエンス・AI応用」（第5回）
A103: ⑪ プログラムの学修成果（学生等が身に付けられる能力等）
B104: 本科目の到達目標は， (1)今後のデジタル社会において，数理・データサイエンス・AIを日常の生活，仕事等の場で使いこなすことができる基礎的素養を主体的に身に付けること， (2)学修した数理・データサイエンス・AIに関する知識・技能をもとに，これらを扱う際には，人間中心の適切な判断ができ，不安なく自らの意志でAI 等の恩恵を享受し，これらを説明し，活用できるようになること， である。
A106: 【参考】
A107: ⑫ 生成AIに関連する授業内容 ※該当がある場合に記載
B108: 教育プログラムを構成する科目に、「数理・データサイエンス・ＡＩ（リテラシーレベル）モデルカリキュラム改訂版」（2024年2月 数理・データサイエンス教育強化拠点コンソーシアム）において追加された生成AIに関連するスキルセットの内容を含む授業（授業内で活用事例などを取り上げる、実際に使用してみるなど）がある場合に、どの科目でどのような授業をどのように実施しているかを記載してください。
B110: ※本項目は各大学の実践例を参考に伺うものであり、認定要件とはなりません。
B111: 講義内容
B112: 該当なし

Sheet 様式２ 履修者等数の実績
S1: 様式２
Q2: ='様式１ プログラムを構成する授業科目'!C2 -> 吉備国際大学
A3: プログラムの履修者数等の実績について
A5: ①プログラム開設年度 | C5: 令和4 | E5: 年度
A7: ②大学等全体の男女別学生数 | E7: 男性 | F7: 941 | G7: 人 | H7: 女性 | I7: 543 | J7: 人 | K7: （ | L7: 合計 | M7: =F7+I7 -> 1484 | N7: 人 | O7: ）
A9: ③履修者・修了者の実績
B11: 学部・学科名称 | C11: 学生数 | D11: 入学 定員 | E11: 収容 定員 | F11: 令和5年度 | H11: 令和4年度 | J11: 令和3年度 | L11: 令和2年度 | N11: 令和元年度 | P11: 平成30年度 | R11: 履修者数 合計 | S11: 履修率
F12: 履修者数 | G12: 修了者数 | H12: 履修者数 | I12: 修了者数 | J12: 履修者数 | K12: 修了者数 | L12: 履修者数 | M12: 修了者数 | N12: 履修者数 | O12: 修了者数 | P12: 履修者数 | Q12: 修了者数
B13: 社会科学部 | C13: 501 | D13: 182 | E13: 684 | F13: 22 | G13: 0 | H13: 3 | I13: 0 | R13: =F13+H13+J13+L13+N13+P13 -> 25 | S13: =R13/E13 -> 0.036549708
B14: 保健医療福祉学部 | C14: 315 | D14: 150 | E14: 580 | F14: 12 | G14: 0 | H14: 0 | I14: 0 | R14: =F14+H14+J14+L14+N14+P14 -> 12 | S14: =R14/E14 -> 0.020689655
B15: 心理学部 | C15: 154 | D15: 40 | E15: 200 | F15: 7 | G15: 0 | H15: 1 | I15: 0 | R15: =F15+H15+J15+L15+N15+P15 -> 8 | S15: =R15/E15 -> 0.04
B16: 農学部 | C16: 220 | D16: 92 | E16: 364 | F16: 47 | G16: 6 | H16: 12 | I16: 0 | R16: =F16+H16+J16+L16+N16+P16 -> 59 | S16: =R16/E16 -> 0.16208791
B17: 外国語学部 | C17: 178 | D17: 50 | E17: 200 | F17: 2 | G17: 0 | H17: 0 | I17: 0 | R17: =F17+H17+J17+L17+N17+P17 -> 2 | S17: =R17/E17 -> 0.01
B18: アニメーション文化学部 | C18: 116 | D18: 40 | E18: 160 | F18: 10 | G18: 0 | H18: 3 | I18: 0 | R18: =F18+H18+J18+L18+N18+P18 -> 13 | S18: =R18/E18 -> 0.08125
R19: =F19+H19+J19+L19+N19+P19 -> 0 | S19: =R19/E19 -> #DIV/0!
R20: =F20+H20+J20+L20+N20+P20 -> 0 | S20: =R20/E20 -> #DIV/0!
R21: =F21+H21+J21+L21+N21+P21 -> 0 | S21: =R21/E21 -> #DIV/0!
R22: =F22+H22+J22+L22+N22+P22 -> 0 | S22: =R22/E22 -> #DIV/0!
R23: =F23+H23+J23+L23+N23+P23 -> 0 | S23: =R23/E23 -> #DIV/0!
R24: =F24+H24+J24+L24+N24+P24 -> 0 | S24: =R24/E24 -> #DIV/0!
R25: =F25+H25+J25+L25+N25+P25 -> 0 | S25: =R25/E25 -> #DIV/0!
R26: =F26+H26+J26+L26+N26+P26 -> 0 | S26: =R26/E26 -> #DIV/0!
R27: =F27+H27+J27+L27+N27+P27 -> 0 | S27: =R27/E27 -> #DIV/0!
R28: =F28+H28+J28+L28+N28+P28 -> 0 | S28: =R28/E28 -> #DIV/0!
R29: =F29+H29+J29+L29+N29+P29 -> 0 | S29: =R29/E29 -> #DIV/0!
R30: =F30+H30+J30+L30+N30+P30 -> 0 | S30: =R30/E30 -> #DIV/0!
... R32: =F32+H32+J32+L32+N32+P32 -> 0 | S32: =R32/E32 -> #DIV/0!
B33: 合 計 | C33: =SUM(C13:C32) -> 1484 | D33: =SUM(D13:D32) -> 554 | E33: =SUM(E13:E32) -> 2188 | F33: =SUM(F13:F32) -> 100 | G33: =SUM(G13:G32) -> 6 | H33: =SUM(H13:H32) -> 19 | I33: =SUM(I13:I32) -> 0 | J33: =SUM(J13:J32) -> 0 | ... R33: =SUM(R13:R32) -> 119 | S33: =R33/E33 -> 0.054387569

Sheet 様式３ 教育の質・履修者数を向上させるための体制・計画
I1: 様式３
G2: 大学等名 | H2: ='様式１ プログラムを構成する授業科目'!C2 -> 吉備国際大学
A4: 教育の質・履修者数を向上させるための体制・計画について
A6: ① | B6: 全学の教員数 | C6: (常勤） | E6: 109 | F6: 人 | G6: （非常勤） | H6: 165 | I6: 人
A8: ② | B8: プログラムの授業を教えている教員数 | H8: 5 | I8: 人
A10: ③ | B10: プログラムの運営責任者
B11: （責任者名） | C11: 佐藤 匡 | G11: （役職名） | H11: 情報教育センター分室長
A13: ④ | B13: プログラムを改善・進化させるための体制（委員会・組織等）
B14: 全学教養教育委員会 情報教育部会
B16: （責任者名） | C16: 佐藤 匡 | G16: （役職名） | H16: 部会長
A18: ⑤ | B18: プログラムを改善・進化させるための体制を定める規則名称
B19: 吉備国際大学委員会規程
A21: ⑥ | B21: 体制の目的
B22: 情報教育部会は、全学教養教育委員会の下に設置され、吉備国際大学における教養教育（情報教育）の編成や教育内容、教育方法の向上や改善などについて審議を行い、教員の情報教育力や学生の学修力の向上を目的としている。数理・データサイエンス・AI教育においては、同プログラムの編成や運営、履修者数の向上に関することについても審議している。
A34: ⑦ | B34: 具体的な構成員
B35: 情報教育部会 部会長 外国語学部 教授 佐藤 匡 情報教育部会 副部会長 アニメーション文化学部 准教授 大谷 卓史 社会科学部 講師 竹岡 志朗 社会科学部 准教授 天岡 寛 保健医療福祉学部 准教授 安福 真弓 保健医療福祉学部 准教授 元田 弘敏 保健医療福祉学部 教授 樋口 博之 保健医療福祉学部 准教授 狩長 弘親 心理学部 講師 村上 勝典 心理学部 准教授 秀 真一郎 農学部 教授 桧原 健一郎 農学部 講師 林 将也 外国語学部 教授 髙木 秀明 アニメーション文化学部 講師 今村 俊介 教務部長 溝井 智子
A48: ⑧ | B48: 履修者数・履修率の向上に向けた計画 ※様式１の「履修必須の有無」で「計画がある」としている場合は詳細について記載すること
B49: 令和５年度実績 | C49: ='様式２ 履修者等数の実績'!S33 -> 0.054387569 | E49: 令和６年度予定 | F49: 0.2 | H49: 令和７年度予定 | I49: 0.4
B50: 令和８年度予定 | C50: 0.6 | E50: 令和９年度予定 | F50: 1 | H50: 収容定員（名） | I50: ='様式２ 履修者等数の実績'!E33 -> 2188
B51: 具体的な計画
B52: 上記の目標を実現するために、本プログラムについてオリエンテーション等でより一層の周知を図るとともに本プログラムの目的と意義について説明し、学生自身が目標を持って履修するよう指導する。また、本プログラムを構成する2つの科目について、学生をTAなどの教育サポートスタッフとして活用するなど履修生が学びやすい環境づくりを行うとともに、令和8年度までに必修化を行い、令和9年度に100％を目指す予定である。
A65: ⑨ | B65: 学部・学科に関係なく希望する学生全員が受講可能となるような必要な体制・取組等
B66: 本プログラムは全学部学科の学生が履修できるものとなっている。また、このプログラムを構成する2つの科目「数理・データサイエンス・AI基礎」（1年次秋学期配当、2単位）では複数のクラスを設けており、学生の履修機会を確保している。また「数理・データサイエンス・AI応用（オンライン）」（2年次春学期配当、2単位）においても、令和6年度の授業から複数のクラスを設けている。
A79: ⑩ | B79: できる限り多くの学生が履修できるような具体的な周知方法・取組
B80: 「数理・データサイエンス・AI受講のすすめ」といった資料を作成し、春学期・秋学期の初めに行っている学科別オリエンテーションの際に全学生へ配布するとともに、プログラムの詳細な説明を行うことで履修を促している。また、学科指導やチューターとの面談で履修指導を行っており、本プログラムを履修するよう指導する。さらに、基礎的な情報リテラシーを涵養する授業である「情報活用」や、「数理・データサイエンス・ＡＩ基礎」の授業において、現代社会における統計学やデータサイエンスの重要性や社会的に注目の高いＡＩについて、その社会や生活への影響を解説して学生の意識を喚起するとともに、本学のプログラムを説明し受講を促す。
A93: ⑪ | B93: できる限り多くの学生が履修・修得できるようなサポート体制
B94: 令和8年度までに「数理・データサイエンス・AI基礎」および「数理・データサイエンス・AI応用」を必修科目とすることで、学生全員が履修する体制の整備を目指している。 本学では、学生と教職員が学務支援システムUniversalPassportおよび、学内グループウェアMicrosoftTeamsを使用して直接コミュニケーション・連絡できる体制を構築している。新入生オリエンテーションにおいては、これらの学内システムの説明を行うとともに、UniversalPassportを通じて、「数理・データサイエンス・AI基礎」および「数理・データサイエンス・AI応用」のシラバスの閲覧・授業履修登録が支障なくできるよう教務課および学科教員が連携して、指導を行っている。また、新入生を含む学生がこれらのシステムを自力で支障なく活用できるよう、情報教育センターおよび教務課、情報システム課が協力し、学内システムの利用法を解説する「ＩＣＴ活用ガイドブック」を作成したうえで、毎年改訂し、上記のUniversalPassportで公開している。上記ガイドブックのメンテナンス・更新作業を容易に行えるよう、現在はWordPressによるブログ化に取り組んでいる。学生の上記システムの利用における質問・問い合わせは、情報教育センター教員が受け付け、必要に応じて、学生に対して情報システム課および教務課のサポートを案内している。
A107: ⑫ | B107: 授業時間内外で学習指導、質問を受け付ける具体的な仕組み
B108: 本学では、教職員と学生が学内グループウェアMicrosoftTeamsおよび、学務支援システムUniversalPassportを使用して直接コミュニケーション・連絡できる体制を構築している。授業内においては、これらのコミュニケーションツールを活用して、教員は授業資料や課題を学生に対して提供できる。また、授業内外において、これらのコミュニケーションツールを活用し、受講学生に対して個別的な学習指導を行うとともに、個々の学生からの質問も直接受け付けている。情報教育センターおよび情報システム課、教務課の協力のもと、上記のサポート体制を通じて、このしくみが実効的に機能するよう対応している。

Sheet 様式４　自己点検・評価
I1: 様式４
H2: 大学等名 | I2: ='様式１ プログラムを構成する授業科目'!C2 -> 吉備国際大学
A3: 自己点検・評価について
A5: ① | B5: プログラムの自己点検・評価を行う体制（委員会・組織等）
B6: 自己点検・自己評価委員会
D8: （責任者名） | E8: 栗田 喜勝 | G8: （役職名） | H8: 委員長
A10: ② | B10: 自己点検・評価体制における意見等
B11: 自己点検・評価の視点 | E11: 自己点検・評価体制における意見・結果・改善に向けた取組等
B12: 学内からの視点
C13: プログラムの履修・修得状況 | E13: 本学では同プログラムは令和4年度より実施しており、学生のプログラム履修・修得状況については、全学教養教育委員会情報教育部会において点検・分析・改善を行い、全学的な履修者数・履修率の向上を図っている。令和4年度は「数理・データサイエンス・AI基礎」が19名と少なかったことから、資料を作成し、学科別オリエンテーションにおいて科目の必要性等の説明を行ったことにより、令和5年度は92名に増加している。
C14: 学修成果 | E14: 本プログラムを構成する「数理・データサイエンス・AI基礎」および「数理・データサイエンス・AI応用」の単位修得状況を見ると、いずれの科目も70%以上の履修者が5段階評価の4以上を取得しており、学生が内容を理解していたと考えられる。また、授業終了後に授業アンケートを実施しており、回答結果を分析し学修成果を把握している。
C15: 学生アンケート等を通じた学生の内容の理解度 | E15: 「数理・データサイエンス・AI基礎」「数理・データサイエンス・AI応用」では授業アンケートを実施している。この結果を通じて授業内容の理解度や学習内容に対する学生の意見を収集し、教育内容の改善を図っている。「数理・データサイエンス・AI基礎」では、「授業内容を分かりやすく説明していた」および「学生の理解に合わせた授業をしていた」といった項目において、約90%の学生が「そう思う」、「どちらかといえばそう思う」と回答している。「数理・データサイエンス・AI応用」では、MicrosoftTeamsのチームの「会議」機能を活用し、各回の授業終了後、学生の授業の理解度（主観的パーセンテージによる回答を求めている）の確認と感想を集約しており、受講者はおおむね理解度が70-80%であると回答している。
C16: 学生アンケート等を通じた後輩等他の学生への推奨度 | E16: 授業アンケートの結果において、「授業の内容は興味や関心が持てるものだった」という項目に対して、90%以上の学生が「そう思う」「どちらかといえばそう思う」と回答しており、後輩学生に対しての推奨といった面においても肯定的な意見が期待できる。
C17: 全学的な履修者数、履修率向上に向けた計画の達成・進捗状況 | E17: 本プログラムを構成する2つの科目については、TAを活用するなどして令和8年度までにカリキュラム変更を行い、必修化を目指している。 令和5年度においては履修者数、履修率の向上を図るため、オリエンテーションにおける本教育プログラムの学生への周知、学生が事前に詳細な学修内容を知る機会の提供、複数の曜日時限のクラスを設ける等、学生が受講しやすい授業環境の整備、LMS(ユニバーサルパスポート)を利用した学生の自主学習環境の整備、授業時間内外における学生指導・質問への対応体制の整備等を行った。
B18: 学外からの視点
C19: 教育プログラム修了者の進路、活躍状況、企業等の評価 | E19: 令和4年度の入学生より開始したプログラムであるため、令和8年度以降に実施する卒業時のアンケート、ならびに卒業から1、2年後に実施する就職先へのアンケートにより、修了者の活躍状況および企業評価等の把握を行う。
C20: 産業界からの視点を含めた教育プログラム内容・手法等への意見 | E20: 自己点検・自己評価委員会において、地元の高等学校、教育委員会や産業界から地元の企業の方を呼び、意見を聞いている。外部評価者からの意見を含めた自己点検・評価の結果を踏まえて、今後、地元の高等学校や教育委員会、産業界からの視点を含めた教育プログラム内容・手法等への意見を反映した改善が随時行われていく予定である。
B21: 数理・データサイエンス・ＡＩを「学ぶ楽しさ」「学ぶことの意義」を理解させること | E21: 令和6年度秋学期からは本学の学内コンビニエンスストアに弁当を納入する設置法人（順正学園）関連企業に依頼し、弁当の納入・販売実績に関するデータ提供を受け、身近なビジネスに関する実データを使って「データを説明する」「データを扱う」学修ができる体制を整備する。また、データサイエンスやAIにかかわる公共放送（NHK）の番組のインターネット配信につき、権利者の利益を不当に害しない範囲で利用する。データサイエンスやAIの最新技術やその応用について学生にわかりやすく、視聴覚に訴求する形で情報提供を行う。なお、本学の設置法人である順正学園は、SARTRASに対して授業目的公衆送信補償金を支払っており、下記のNHKの説明からこのような利用が可能と判断している。 https://www.nhk.or.jp/nijiriyou/kyouiku.html
B22: 内容・水準を維持・向上しつつ、より「分かりやすい」授業とすること ※社会の変化や生成AI等の技術の発展を踏まえて教育内容を継続的に見直すなど、より教育効果の高まる授業内容・方法とするための取組や仕組みについても該当があれば記載 | E22: 本学教育へ反映させることを狙いとして、卒業生の就職先へのヒアリングにより、本学の教育に期待することや産業界で求められている資質・能力、本学卒業生に対する満足度等の情報収集を行い、企業との教育コンテンツの共同開発等を通じて、産業界からのニーズの把握に取り組んでいる。また、定期的に「数理・データサイエンス・AI基礎」および「数理・データサイエンス・AI応用」の教員が気軽に会話できる雰囲気のミーティング（「座談会」と称している）を行い、内容・水準を維持・向上しつつ、より「分かりやすい」授業とするため、それぞれの授業の取り組みや、数理・データサイエンス・AIにかかわる最近の技術発展や社会・経済の変化について情報・意見交換を行っている。
